{
  "id": "android-swipe-refresh-layout",
  "name": "Android Developers: Add swipe-to-refresh to your app",
  "type": "platform-guideline",
  "url": "https://developer.android.com/develop/ui/views/touch-and-input/swipe/add-swipe-interface",
  "publisher": "Android Developers",
  "checkedAt": "2026-06-13",
  "notes": "Documents SwipeRefreshLayout for adding a swipe-to-refresh widget around scrollable content and explicitly recommends an action-bar refresh item so users who cannot perform the gesture can still trigger the same update."
}
