{
  "id": "atlassian-assets-comments",
  "name": "Atlassian Support: Add, edit, or delete comments in objects",
  "type": "product-example",
  "url": "https://support.atlassian.com/assets/docs/add-edit-or-delete-comments/",
  "publisher": "Atlassian Support",
  "checkedAt": "2026-06-11",
  "notes": "Documents comments attached to objects rather than work items, permission requirements, finding comments in an Activity area, adding text, editing a hovered comment, deleting a comment, and warning that deletion cannot be undone."
}
